regularize/__init__.py
regularize/exceptions.py
regularize/expression.py
regularize/find.py
regularize/flag.py
regularize/replace.py
regularize-0.0.7.dist-info/LICENSE
regularize-0.0.7.dist-info/METADATA
regularize-0.0.7.dist-info/WHEEL
regularize-0.0.7.dist-info/top_level.txt
regularize-0.0.7.dist-info/RECORD
