Metadata-Version: 2.1
Name: regularize
Version: 0.0.7
Summary: Regular Expression Builder
Home-page: https://github.com/georgepsarakis/regularize
Author: George Psarakis
License: MIT
Platform: UNKNOWN
Classifier: Intended Audience :: Developers
Classifier: Intended Audience :: System Administrators
Classifier: Operating System :: POSIX :: Linux
Classifier: Development Status :: 2 - Pre-Alpha
Classifier: Programming Language :: Python :: 3
Classifier: License :: OSI Approved :: MIT License
Provides-Extra: dev
Requires-Dist: pytest (==6.1.0) ; extra == 'dev'
Requires-Dist: flake8 (==3.8.4) ; extra == 'dev'
Requires-Dist: pytest-cov (==2.10.1) ; extra == 'dev'
